tprtools/__init__.py
tprtools/jsonpath.py
thiliapr_tools-1.0.2.dist-info/LICENSE
thiliapr_tools-1.0.2.dist-info/METADATA
thiliapr_tools-1.0.2.dist-info/WHEEL
thiliapr_tools-1.0.2.dist-info/top_level.txt
thiliapr_tools-1.0.2.dist-info/RECORD
