Metadata-Version: 2.1
Name: thiliapr-tools
Version: 1.0.2
Summary: A library by thiliapr.
Author: thiliapr
Project-URL: Homepage, https://github.com/thiliapr/python3-tprtools
Project-URL: Issues, https://github.com/thiliapr/python3-tprtools/issues
Classifier: Programming Language :: Python :: 3
Classifier: License :: OSI Approved :: GNU General Public License v3 or later (GPLv3+)
Classifier: Operating System :: OS Independent
Requires-Python: >=3.6
License-File: LICENSE
